{
  "name": "else",
  "subject": 196,
  "date": null,
  "paths": {
    "Pen": {
      "strokes":
    [
      {
        "x": 6970,
        "y": 8559,
        "w": null,
        "z": null,
        "alpha": null,
        "beta": null,
        "gamma": null,
        "t": 915,
        "stroke_id": 0
      },
      {
        "x": 6972,
        "y": 8558,
        "w": null,
        "z": null,
        "alpha": null,
        "beta": null,
        "gamma": null,
        "t": 916,
        "stroke_id": 0
      },
      {
        "x": 7007,
        "y": 8542,
        "w": null,
        "z": null,
        "alpha": null,
        "beta": null,
        "gamma": null,
        "t": 917,
        "stroke_id": 0
      },
      {
        "x": 7032,
        "y": 8521,
        "w": null,
        "z": null,
        "alpha": null,
        "beta": null,
        "gamma": null,
        "t": 918,
        "stroke_id": 0
      },
      {
        "x": 7068,
        "y": 8495,
        "w": null,
        "z": null,
        "alpha": null,
        "beta": null,
        "gamma": null,
        "t": 919,
        "stroke_id": 0
      },
      {
        "x": 7103,
        "y": 8461,
        "w": null,
        "z": null,
        "alpha": null,
        "beta": null,
        "gamma": null,
        "t": 920,
        "stroke_id": 0
      },
      {
        "x": 7142,
        "y": 8419,
        "w": null,
        "z": null,
        "alpha": null,
        "beta": null,
        "gamma": null,
        "t": 921,
        "stroke_id": 0
      },
      {
        "x": 7177,
        "y": 8368,
        "w": null,
        "z": null,
        "alpha": null,
        "beta": null,
        "gamma": null,
        "t": 922,
        "stroke_id": 0
      },
      {
        "x": 7211,
        "y": 8317,
        "w": null,
        "z": null,
        "alpha": null,
        "beta": null,
        "gamma": null,
        "t": 923,
        "stroke_id": 0
      },
      {
        "x": 7240,
        "y": 8265,
        "w": null,
        "z": null,
        "alpha": null,
        "beta": null,
        "gamma": null,
        "t": 924,
        "stroke_id": 0
      },
      {
        "x": 7263,
        "y": 8213,
        "w": null,
        "z": null,
        "alpha": null,
        "beta": null,
        "gamma": null,
        "t": 925,
        "stroke_id": 0
      },
      {
        "x": 7280,
        "y": 8160,
        "w": null,
        "z": null,
        "alpha": null,
        "beta": null,
        "gamma": null,
        "t": 926,
        "stroke_id": 0
      },
      {
        "x": 7293,
        "y": 8110,
        "w": null,
        "z": null,
        "alpha": null,
        "beta": null,
        "gamma": null,
        "t": 927,
        "stroke_id": 0
      },
      {
        "x": 7299,
        "y": 8062,
        "w": null,
        "z": null,
        "alpha": null,
        "beta": null,
        "gamma": null,
        "t": 928,
        "stroke_id": 0
      },
      {
        "x": 7298,
        "y": 8022,
        "w": null,
        "z": null,
        "alpha": null,
        "beta": null,
        "gamma": null,
        "t": 929,
        "stroke_id": 0
      },
      {
        "x": 7293,
        "y": 7990,
        "w": null,
        "z": null,
        "alpha": null,
        "beta": null,
        "gamma": null,
        "t": 930,
        "stroke_id": 0
      },
      {
        "x": 7282,
        "y": 7965,
        "w": null,
        "z": null,
        "alpha": null,
        "beta": null,
        "gamma": null,
        "t": 931,
        "stroke_id": 0
      },
      {
        "x": 7268,
        "y": 7945,
        "w": null,
        "z": null,
        "alpha": null,
        "beta": null,
        "gamma": null,
        "t": 932,
        "stroke_id": 0
      },
      {
        "x": 7254,
        "y": 7934,
        "w": null,
        "z": null,
        "alpha": null,
        "beta": null,
        "gamma": null,
        "t": 933,
        "stroke_id": 0
      },
      {
        "x": 7221,
        "y": 7934,
        "w": null,
        "z": null,
        "alpha": null,
        "beta": null,
        "gamma": null,
        "t": 934,
        "stroke_id": 0
      },
      {
        "x": 7205,
        "y": 7950,
        "w": null,
        "z": null,
        "alpha": null,
        "beta": null,
        "gamma": null,
        "t": 935,
        "stroke_id": 0
      },
      {
        "x": 7191,
        "y": 7974,
        "w": null,
        "z": null,
        "alpha": null,
        "beta": null,
        "gamma": null,
        "t": 936,
        "stroke_id": 0
      },
      {
        "x": 7174,
        "y": 8010,
        "w": null,
        "z": null,
        "alpha": null,
        "beta": null,
        "gamma": null,
        "t": 937,
        "stroke_id": 0
      },
      {
        "x": 7160,
        "y": 8051,
        "w": null,
        "z": null,
        "alpha": null,
        "beta": null,
        "gamma": null,
        "t": 938,
        "stroke_id": 0
      },
      {
        "x": 7146,
        "y": 8107,
        "w": null,
        "z": null,
        "alpha": null,
        "beta": null,
        "gamma": null,
        "t": 939,
        "stroke_id": 0
      },
      {
        "x": 7134,
        "y": 8174,
        "w": null,
        "z": null,
        "alpha": null,
        "beta": null,
        "gamma": null,
        "t": 940,
        "stroke_id": 0
      },
      {
        "x": 7126,
        "y": 8238,
        "w": null,
        "z": null,
        "alpha": null,
        "beta": null,
        "gamma": null,
        "t": 941,
        "stroke_id": 0
      },
      {
        "x": 7122,
        "y": 8306,
        "w": null,
        "z": null,
        "alpha": null,
        "beta": null,
        "gamma": null,
        "t": 942,
        "stroke_id": 0
      },
      {
        "x": 7120,
        "y": 8364,
        "w": null,
        "z": null,
        "alpha": null,
        "beta": null,
        "gamma": null,
        "t": 943,
        "stroke_id": 0
      },
      {
        "x": 7129,
        "y": 8421,
        "w": null,
        "z": null,
        "alpha": null,
        "beta": null,
        "gamma": null,
        "t": 944,
        "stroke_id": 0
      },
      {
        "x": 7143,
        "y": 8467,
        "w": null,
        "z": null,
        "alpha": null,
        "beta": null,
        "gamma": null,
        "t": 945,
        "stroke_id": 0
      },
      {
        "x": 7170,
        "y": 8502,
        "w": null,
        "z": null,
        "alpha": null,
        "beta": null,
        "gamma": null,
        "t": 946,
        "stroke_id": 0
      },
      {
        "x": 7198,
        "y": 8517,
        "w": null,
        "z": null,
        "alpha": null,
        "beta": null,
        "gamma": null,
        "t": 947,
        "stroke_id": 0
      },
      {
        "x": 7230,
        "y": 8517,
        "w": null,
        "z": null,
        "alpha": null,
        "beta": null,
        "gamma": null,
        "t": 948,
        "stroke_id": 0
      },
      {
        "x": 7271,
        "y": 8505,
        "w": null,
        "z": null,
        "alpha": null,
        "beta": null,
        "gamma": null,
        "t": 949,
        "stroke_id": 0
      },
      {
        "x": 7313,
        "y": 8488,
        "w": null,
        "z": null,
        "alpha": null,
        "beta": null,
        "gamma": null,
        "t": 950,
        "stroke_id": 0
      },
      {
        "x": 7358,
        "y": 8462,
        "w": null,
        "z": null,
        "alpha": null,
        "beta": null,
        "gamma": null,
        "t": 951,
        "stroke_id": 0
      },
      {
        "x": 7400,
        "y": 8429,
        "w": null,
        "z": null,
        "alpha": null,
        "beta": null,
        "gamma": null,
        "t": 952,
        "stroke_id": 0
      },
      {
        "x": 7438,
        "y": 8385,
        "w": null,
        "z": null,
        "alpha": null,
        "beta": null,
        "gamma": null,
        "t": 953,
        "stroke_id": 0
      },
      {
        "x": 7475,
        "y": 8338,
        "w": null,
        "z": null,
        "alpha": null,
        "beta": null,
        "gamma": null,
        "t": 954,
        "stroke_id": 0
      },
      {
        "x": 7508,
        "y": 8288,
        "w": null,
        "z": null,
        "alpha": null,
        "beta": null,
        "gamma": null,
        "t": 955,
        "stroke_id": 0
      },
      {
        "x": 7541,
        "y": 8233,
        "w": null,
        "z": null,
        "alpha": null,
        "beta": null,
        "gamma": null,
        "t": 956,
        "stroke_id": 0
      },
      {
        "x": 7569,
        "y": 8176,
        "w": null,
        "z": null,
        "alpha": null,
        "beta": null,
        "gamma": null,
        "t": 957,
        "stroke_id": 0
      },
      {
        "x": 7591,
        "y": 8118,
        "w": null,
        "z": null,
        "alpha": null,
        "beta": null,
        "gamma": null,
        "t": 958,
        "stroke_id": 0
      },
      {
        "x": 7609,
        "y": 8054,
        "w": null,
        "z": null,
        "alpha": null,
        "beta": null,
        "gamma": null,
        "t": 959,
        "stroke_id": 0
      },
      {
        "x": 7626,
        "y": 7989,
        "w": null,
        "z": null,
        "alpha": null,
        "beta": null,
        "gamma": null,
        "t": 960,
        "stroke_id": 0
      },
      {
        "x": 7640,
        "y": 7928,
        "w": null,
        "z": null,
        "alpha": null,
        "beta": null,
        "gamma": null,
        "t": 961,
        "stroke_id": 0
      },
      {
        "x": 7650,
        "y": 7867,
        "w": null,
        "z": null,
        "alpha": null,
        "beta": null,
        "gamma": null,
        "t": 962,
        "stroke_id": 0
      },
      {
        "x": 7659,
        "y": 7807,
        "w": null,
        "z": null,
        "alpha": null,
        "beta": null,
        "gamma": null,
        "t": 963,
        "stroke_id": 0
      },
      {
        "x": 7668,
        "y": 7753,
        "w": null,
        "z": null,
        "alpha": null,
        "beta": null,
        "gamma": null,
        "t": 964,
        "stroke_id": 0
      },
      {
        "x": 7675,
        "y": 7699,
        "w": null,
        "z": null,
        "alpha": null,
        "beta": null,
        "gamma": null,
        "t": 965,
        "stroke_id": 0
      },
      {
        "x": 7680,
        "y": 7642,
        "w": null,
        "z": null,
        "alpha": null,
        "beta": null,
        "gamma": null,
        "t": 966,
        "stroke_id": 0
      },
      {
        "x": 7683,
        "y": 7591,
        "w": null,
        "z": null,
        "alpha": null,
        "beta": null,
        "gamma": null,
        "t": 967,
        "stroke_id": 0
      },
      {
        "x": 7686,
        "y": 7549,
        "w": null,
        "z": null,
        "alpha": null,
        "beta": null,
        "gamma": null,
        "t": 968,
        "stroke_id": 0
      },
      {
        "x": 7686,
        "y": 7515,
        "w": null,
        "z": null,
        "alpha": null,
        "beta": null,
        "gamma": null,
        "t": 969,
        "stroke_id": 0
      },
      {
        "x": 7684,
        "y": 7487,
        "w": null,
        "z": null,
        "alpha": null,
        "beta": null,
        "gamma": null,
        "t": 970,
        "stroke_id": 0
      },
      {
        "x": 7683,
        "y": 7465,
        "w": null,
        "z": null,
        "alpha": null,
        "beta": null,
        "gamma": null,
        "t": 971,
        "stroke_id": 0
      },
      {
        "x": 7678,
        "y": 7446,
        "w": null,
        "z": null,
        "alpha": null,
        "beta": null,
        "gamma": null,
        "t": 972,
        "stroke_id": 0
      },
      {
        "x": 7657,
        "y": 7455,
        "w": null,
        "z": null,
        "alpha": null,
        "beta": null,
        "gamma": null,
        "t": 973,
        "stroke_id": 0
      },
      {
        "x": 7649,
        "y": 7483,
        "w": null,
        "z": null,
        "alpha": null,
        "beta": null,
        "gamma": null,
        "t": 974,
        "stroke_id": 0
      },
      {
        "x": 7638,
        "y": 7521,
        "w": null,
        "z": null,
        "alpha": null,
        "beta": null,
        "gamma": null,
        "t": 975,
        "stroke_id": 0
      },
      {
        "x": 7628,
        "y": 7570,
        "w": null,
        "z": null,
        "alpha": null,
        "beta": null,
        "gamma": null,
        "t": 976,
        "stroke_id": 0
      },
      {
        "x": 7615,
        "y": 7628,
        "w": null,
        "z": null,
        "alpha": null,
        "beta": null,
        "gamma": null,
        "t": 977,
        "stroke_id": 0
      },
      {
        "x": 7604,
        "y": 7701,
        "w": null,
        "z": null,
        "alpha": null,
        "beta": null,
        "gamma": null,
        "t": 978,
        "stroke_id": 0
      },
      {
        "x": 7594,
        "y": 7782,
        "w": null,
        "z": null,
        "alpha": null,
        "beta": null,
        "gamma": null,
        "t": 979,
        "stroke_id": 0
      },
      {
        "x": 7586,
        "y": 7872,
        "w": null,
        "z": null,
        "alpha": null,
        "beta": null,
        "gamma": null,
        "t": 980,
        "stroke_id": 0
      },
      {
        "x": 7581,
        "y": 7951,
        "w": null,
        "z": null,
        "alpha": null,
        "beta": null,
        "gamma": null,
        "t": 981,
        "stroke_id": 0
      },
      {
        "x": 7578,
        "y": 8029,
        "w": null,
        "z": null,
        "alpha": null,
        "beta": null,
        "gamma": null,
        "t": 982,
        "stroke_id": 0
      },
      {
        "x": 7581,
        "y": 8105,
        "w": null,
        "z": null,
        "alpha": null,
        "beta": null,
        "gamma": null,
        "t": 983,
        "stroke_id": 0
      },
      {
        "x": 7591,
        "y": 8179,
        "w": null,
        "z": null,
        "alpha": null,
        "beta": null,
        "gamma": null,
        "t": 984,
        "stroke_id": 0
      },
      {
        "x": 7608,
        "y": 8241,
        "w": null,
        "z": null,
        "alpha": null,
        "beta": null,
        "gamma": null,
        "t": 985,
        "stroke_id": 0
      },
      {
        "x": 7631,
        "y": 8293,
        "w": null,
        "z": null,
        "alpha": null,
        "beta": null,
        "gamma": null,
        "t": 986,
        "stroke_id": 0
      },
      {
        "x": 7659,
        "y": 8334,
        "w": null,
        "z": null,
        "alpha": null,
        "beta": null,
        "gamma": null,
        "t": 987,
        "stroke_id": 0
      },
      {
        "x": 7694,
        "y": 8366,
        "w": null,
        "z": null,
        "alpha": null,
        "beta": null,
        "gamma": null,
        "t": 988,
        "stroke_id": 0
      },
      {
        "x": 7735,
        "y": 8382,
        "w": null,
        "z": null,
        "alpha": null,
        "beta": null,
        "gamma": null,
        "t": 989,
        "stroke_id": 0
      },
      {
        "x": 7779,
        "y": 8385,
        "w": null,
        "z": null,
        "alpha": null,
        "beta": null,
        "gamma": null,
        "t": 990,
        "stroke_id": 0
      },
      {
        "x": 7823,
        "y": 8373,
        "w": null,
        "z": null,
        "alpha": null,
        "beta": null,
        "gamma": null,
        "t": 991,
        "stroke_id": 0
      },
      {
        "x": 7868,
        "y": 8345,
        "w": null,
        "z": null,
        "alpha": null,
        "beta": null,
        "gamma": null,
        "t": 992,
        "stroke_id": 0
      },
      {
        "x": 7909,
        "y": 8308,
        "w": null,
        "z": null,
        "alpha": null,
        "beta": null,
        "gamma": null,
        "t": 993,
        "stroke_id": 0
      },
      {
        "x": 7948,
        "y": 8261,
        "w": null,
        "z": null,
        "alpha": null,
        "beta": null,
        "gamma": null,
        "t": 994,
        "stroke_id": 0
      },
      {
        "x": 7979,
        "y": 8212,
        "w": null,
        "z": null,
        "alpha": null,
        "beta": null,
        "gamma": null,
        "t": 995,
        "stroke_id": 0
      },
      {
        "x": 8004,
        "y": 8157,
        "w": null,
        "z": null,
        "alpha": null,
        "beta": null,
        "gamma": null,
        "t": 996,
        "stroke_id": 0
      },
      {
        "x": 8021,
        "y": 8106,
        "w": null,
        "z": null,
        "alpha": null,
        "beta": null,
        "gamma": null,
        "t": 997,
        "stroke_id": 0
      },
      {
        "x": 8032,
        "y": 8059,
        "w": null,
        "z": null,
        "alpha": null,
        "beta": null,
        "gamma": null,
        "t": 998,
        "stroke_id": 0
      },
      {
        "x": 8038,
        "y": 8012,
        "w": null,
        "z": null,
        "alpha": null,
        "beta": null,
        "gamma": null,
        "t": 999,
        "stroke_id": 0
      },
      {
        "x": 8038,
        "y": 7978,
        "w": null,
        "z": null,
        "alpha": null,
        "beta": null,
        "gamma": null,
        "t": 1000,
        "stroke_id": 0
      },
      {
        "x": 8034,
        "y": 7950,
        "w": null,
        "z": null,
        "alpha": null,
        "beta": null,
        "gamma": null,
        "t": 1001,
        "stroke_id": 0
      },
      {
        "x": 8030,
        "y": 7927,
        "w": null,
        "z": null,
        "alpha": null,
        "beta": null,
        "gamma": null,
        "t": 1002,
        "stroke_id": 0
      },
      {
        "x": 8024,
        "y": 7909,
        "w": null,
        "z": null,
        "alpha": null,
        "beta": null,
        "gamma": null,
        "t": 1003,
        "stroke_id": 0
      },
      {
        "x": 8020,
        "y": 7896,
        "w": null,
        "z": null,
        "alpha": null,
        "beta": null,
        "gamma": null,
        "t": 1004,
        "stroke_id": 0
      },
      {
        "x": 8025,
        "y": 7907,
        "w": null,
        "z": null,
        "alpha": null,
        "beta": null,
        "gamma": null,
        "t": 1005,
        "stroke_id": 0
      },
      {
        "x": 8034,
        "y": 7927,
        "w": null,
        "z": null,
        "alpha": null,
        "beta": null,
        "gamma": null,
        "t": 1006,
        "stroke_id": 0
      },
      {
        "x": 8043,
        "y": 7955,
        "w": null,
        "z": null,
        "alpha": null,
        "beta": null,
        "gamma": null,
        "t": 1007,
        "stroke_id": 0
      },
      {
        "x": 8053,
        "y": 7989,
        "w": null,
        "z": null,
        "alpha": null,
        "beta": null,
        "gamma": null,
        "t": 1008,
        "stroke_id": 0
      },
      {
        "x": 8066,
        "y": 8029,
        "w": null,
        "z": null,
        "alpha": null,
        "beta": null,
        "gamma": null,
        "t": 1009,
        "stroke_id": 0
      },
      {
        "x": 8075,
        "y": 8072,
        "w": null,
        "z": null,
        "alpha": null,
        "beta": null,
        "gamma": null,
        "t": 1010,
        "stroke_id": 0
      },
      {
        "x": 8082,
        "y": 8118,
        "w": null,
        "z": null,
        "alpha": null,
        "beta": null,
        "gamma": null,
        "t": 1011,
        "stroke_id": 0
      },
      {
        "x": 8091,
        "y": 8166,
        "w": null,
        "z": null,
        "alpha": null,
        "beta": null,
        "gamma": null,
        "t": 1012,
        "stroke_id": 0
      },
      {
        "x": 8096,
        "y": 8214,
        "w": null,
        "z": null,
        "alpha": null,
        "beta": null,
        "gamma": null,
        "t": 1013,
        "stroke_id": 0
      },
      {
        "x": 8099,
        "y": 8255,
        "w": null,
        "z": null,
        "alpha": null,
        "beta": null,
        "gamma": null,
        "t": 1014,
        "stroke_id": 0
      },
      {
        "x": 8098,
        "y": 8294,
        "w": null,
        "z": null,
        "alpha": null,
        "beta": null,
        "gamma": null,
        "t": 1015,
        "stroke_id": 0
      },
      {
        "x": 8094,
        "y": 8327,
        "w": null,
        "z": null,
        "alpha": null,
        "beta": null,
        "gamma": null,
        "t": 1016,
        "stroke_id": 0
      },
      {
        "x": 8085,
        "y": 8359,
        "w": null,
        "z": null,
        "alpha": null,
        "beta": null,
        "gamma": null,
        "t": 1017,
        "stroke_id": 0
      },
      {
        "x": 8075,
        "y": 8382,
        "w": null,
        "z": null,
        "alpha": null,
        "beta": null,
        "gamma": null,
        "t": 1018,
        "stroke_id": 0
      },
      {
        "x": 8044,
        "y": 8405,
        "w": null,
        "z": null,
        "alpha": null,
        "beta": null,
        "gamma": null,
        "t": 1019,
        "stroke_id": 0
      },
      {
        "x": 8024,
        "y": 8404,
        "w": null,
        "z": null,
        "alpha": null,
        "beta": null,
        "gamma": null,
        "t": 1020,
        "stroke_id": 0
      },
      {
        "x": 8002,
        "y": 8400,
        "w": null,
        "z": null,
        "alpha": null,
        "beta": null,
        "gamma": null,
        "t": 1021,
        "stroke_id": 0
      },
      {
        "x": 7961,
        "y": 8382,
        "w": null,
        "z": null,
        "alpha": null,
        "beta": null,
        "gamma": null,
        "t": 1022,
        "stroke_id": 0
      },
      {
        "x": 7944,
        "y": 8368,
        "w": null,
        "z": null,
        "alpha": null,
        "beta": null,
        "gamma": null,
        "t": 1023,
        "stroke_id": 0
      },
      {
        "x": 7932,
        "y": 8343,
        "w": null,
        "z": null,
        "alpha": null,
        "beta": null,
        "gamma": null,
        "t": 1024,
        "stroke_id": 0
      },
      {
        "x": 7960,
        "y": 8334,
        "w": null,
        "z": null,
        "alpha": null,
        "beta": null,
        "gamma": null,
        "t": 1025,
        "stroke_id": 0
      },
      {
        "x": 7985,
        "y": 8330,
        "w": null,
        "z": null,
        "alpha": null,
        "beta": null,
        "gamma": null,
        "t": 1026,
        "stroke_id": 0
      },
      {
        "x": 8016,
        "y": 8325,
        "w": null,
        "z": null,
        "alpha": null,
        "beta": null,
        "gamma": null,
        "t": 1027,
        "stroke_id": 0
      },
      {
        "x": 8052,
        "y": 8320,
        "w": null,
        "z": null,
        "alpha": null,
        "beta": null,
        "gamma": null,
        "t": 1028,
        "stroke_id": 0
      },
      {
        "x": 8180,
        "y": 8289,
        "w": null,
        "z": null,
        "alpha": null,
        "beta": null,
        "gamma": null,
        "t": 1029,
        "stroke_id": 0
      },
      {
        "x": 8207,
        "y": 8271,
        "w": null,
        "z": null,
        "alpha": null,
        "beta": null,
        "gamma": null,
        "t": 1030,
        "stroke_id": 0
      },
      {
        "x": 8230,
        "y": 8252,
        "w": null,
        "z": null,
        "alpha": null,
        "beta": null,
        "gamma": null,
        "t": 1031,
        "stroke_id": 0
      },
      {
        "x": 8248,
        "y": 8231,
        "w": null,
        "z": null,
        "alpha": null,
        "beta": null,
        "gamma": null,
        "t": 1032,
        "stroke_id": 0
      },
      {
        "x": 8265,
        "y": 8207,
        "w": null,
        "z": null,
        "alpha": null,
        "beta": null,
        "gamma": null,
        "t": 1033,
        "stroke_id": 0
      },
      {
        "x": 8282,
        "y": 8181,
        "w": null,
        "z": null,
        "alpha": null,
        "beta": null,
        "gamma": null,
        "t": 1034,
        "stroke_id": 0
      },
      {
        "x": 8294,
        "y": 8151,
        "w": null,
        "z": null,
        "alpha": null,
        "beta": null,
        "gamma": null,
        "t": 1035,
        "stroke_id": 0
      },
      {
        "x": 8303,
        "y": 8119,
        "w": null,
        "z": null,
        "alpha": null,
        "beta": null,
        "gamma": null,
        "t": 1036,
        "stroke_id": 0
      },
      {
        "x": 8307,
        "y": 8083,
        "w": null,
        "z": null,
        "alpha": null,
        "beta": null,
        "gamma": null,
        "t": 1037,
        "stroke_id": 0
      },
      {
        "x": 8309,
        "y": 8055,
        "w": null,
        "z": null,
        "alpha": null,
        "beta": null,
        "gamma": null,
        "t": 1038,
        "stroke_id": 0
      },
      {
        "x": 8312,
        "y": 8030,
        "w": null,
        "z": null,
        "alpha": null,
        "beta": null,
        "gamma": null,
        "t": 1039,
        "stroke_id": 0
      },
      {
        "x": 8309,
        "y": 7983,
        "w": null,
        "z": null,
        "alpha": null,
        "beta": null,
        "gamma": null,
        "t": 1040,
        "stroke_id": 0
      },
      {
        "x": 8304,
        "y": 7965,
        "w": null,
        "z": null,
        "alpha": null,
        "beta": null,
        "gamma": null,
        "t": 1041,
        "stroke_id": 0
      },
      {
        "x": 8291,
        "y": 7945,
        "w": null,
        "z": null,
        "alpha": null,
        "beta": null,
        "gamma": null,
        "t": 1042,
        "stroke_id": 0
      },
      {
        "x": 8271,
        "y": 7956,
        "w": null,
        "z": null,
        "alpha": null,
        "beta": null,
        "gamma": null,
        "t": 1043,
        "stroke_id": 0
      },
      {
        "x": 8258,
        "y": 7976,
        "w": null,
        "z": null,
        "alpha": null,
        "beta": null,
        "gamma": null,
        "t": 1044,
        "stroke_id": 0
      },
      {
        "x": 8242,
        "y": 8007,
        "w": null,
        "z": null,
        "alpha": null,
        "beta": null,
        "gamma": null,
        "t": 1045,
        "stroke_id": 0
      },
      {
        "x": 8229,
        "y": 8046,
        "w": null,
        "z": null,
        "alpha": null,
        "beta": null,
        "gamma": null,
        "t": 1046,
        "stroke_id": 0
      },
      {
        "x": 8215,
        "y": 8095,
        "w": null,
        "z": null,
        "alpha": null,
        "beta": null,
        "gamma": null,
        "t": 1047,
        "stroke_id": 0
      },
      {
        "x": 8203,
        "y": 8151,
        "w": null,
        "z": null,
        "alpha": null,
        "beta": null,
        "gamma": null,
        "t": 1048,
        "stroke_id": 0
      },
      {
        "x": 8194,
        "y": 8205,
        "w": null,
        "z": null,
        "alpha": null,
        "beta": null,
        "gamma": null,
        "t": 1049,
        "stroke_id": 0
      },
      {
        "x": 8193,
        "y": 8260,
        "w": null,
        "z": null,
        "alpha": null,
        "beta": null,
        "gamma": null,
        "t": 1050,
        "stroke_id": 0
      },
      {
        "x": 8200,
        "y": 8307,
        "w": null,
        "z": null,
        "alpha": null,
        "beta": null,
        "gamma": null,
        "t": 1051,
        "stroke_id": 0
      },
      {
        "x": 8219,
        "y": 8346,
        "w": null,
        "z": null,
        "alpha": null,
        "beta": null,
        "gamma": null,
        "t": 1052,
        "stroke_id": 0
      },
      {
        "x": 8249,
        "y": 8376,
        "w": null,
        "z": null,
        "alpha": null,
        "beta": null,
        "gamma": null,
        "t": 1053,
        "stroke_id": 0
      },
      {
        "x": 8293,
        "y": 8394,
        "w": null,
        "z": null,
        "alpha": null,
        "beta": null,
        "gamma": null,
        "t": 1054,
        "stroke_id": 0
      },
      {
        "x": 8354,
        "y": 8405,
        "w": null,
        "z": null,
        "alpha": null,
        "beta": null,
        "gamma": null,
        "t": 1055,
        "stroke_id": 0
      },
      {
        "x": 8415,
        "y": 8394,
        "w": null,
        "z": null,
        "alpha": null,
        "beta": null,
        "gamma": null,
        "t": 1056,
        "stroke_id": 0
      },
      {
        "x": 8479,
        "y": 8378,
        "w": null,
        "z": null,
        "alpha": null,
        "beta": null,
        "gamma": null,
        "t": 1057,
        "stroke_id": 0
      },
      {
        "x": 8540,
        "y": 8359,
        "w": null,
        "z": null,
        "alpha": null,
        "beta": null,
        "gamma": null,
        "t": 1058,
        "stroke_id": 0
      }
    ]
    }
  },
  "device": {
    "osBrowserInfo": "HP TabletPC TC 1100, operated with Windows XP TabletPC Edition",
    "resolutionHeight": 600,
    "resolutionWidth": 800,
    "windowHeight": null,
    "windowWidth": null,
    "pixelRatio": null,
    "mouse": false,
    "pen": true,
    "finger": false,
    "acceleration": false,
    "webcam": false
  }
}